example_package_YanChengxin/__init__.py
example_package_YanChengxin/example.py
example_package_YanChengxin-2024.6.29.8.dist-info/LICENSE
example_package_YanChengxin-2024.6.29.8.dist-info/METADATA
example_package_YanChengxin-2024.6.29.8.dist-info/WHEEL
example_package_YanChengxin-2024.6.29.8.dist-info/top_level.txt
example_package_YanChengxin-2024.6.29.8.dist-info/RECORD
