Metadata-Version: 2.1
Name: example_package_YanChengxin
Version: 2024.6.29.8
Summary: 一个简单的作为学习用途的包
Author-email: YanChengxin <yan.cheng.xin@foxmail.com>
Project-URL: Homepage, https://github.com/pypa/sampleproject
Project-URL: Issues, https://github.com/pypa/sampleproject/issues
Classifier: Programming Language :: Python :: 3
Classifier: License :: OSI Approved :: MIT License
Classifier: Operating System :: OS Independent
Requires-Python: >=3.8
License-File: LICENSE
